Xomics_Clara_Mariam/.Rhistory
Xomics_Clara_Mariam/__init__.py
Xomics_Clara_Mariam/script_annot_visu_final.py
Xomics_Clara_Mariam/script_get_gene.py
xomics_clara_mariam-0.1.0.dist-info/METADATA
xomics_clara_mariam-0.1.0.dist-info/WHEEL
xomics_clara_mariam-0.1.0.dist-info/RECORD
