Metadata-Version: 2.3
Name: Xomics_Clara_Mariam
Version: 0.1.0
Summary: Add your description here
Author: mariam
Author-email: clara <clara.centa@gmail.com>
Requires-Python: >=3.10
Requires-Dist: matplotlib>=3.9.2
